LICENSE
README.md
setup.py
deploy_config_generator/__init__.py
deploy_config_generator/__main__.py
deploy_config_generator/deploy_config.py
deploy_config_generator/display.py
deploy_config_generator/errors.py
deploy_config_generator/secrets.py
deploy_config_generator/site_config.py
deploy_config_generator/template.py
deploy_config_generator/utils.py
deploy_config_generator/vars.py
deploy_config_generator.egg-info/PKG-INFO
deploy_config_generator.egg-info/SOURCES.txt
deploy_config_generator.egg-info/dependency_links.txt
deploy_config_generator.egg-info/entry_points.txt
deploy_config_generator.egg-info/not-zip-safe
deploy_config_generator.egg-info/requires.txt
deploy_config_generator.egg-info/top_level.txt
deploy_config_generator/output/__init__.py
deploy_config_generator/output/dummy.py
deploy_config_generator/output/kongfig.py
deploy_config_generator/output/kube_common.py
deploy_config_generator/output/kube_configmap.py
deploy_config_generator/output/kube_cronjob.py
deploy_config_generator/output/kube_deployment.py
deploy_config_generator/output/kube_dnsendpoint.py
deploy_config_generator/output/kube_ingress.py
deploy_config_generator/output/kube_job.py
deploy_config_generator/output/kube_kong_consumer.py
deploy_config_generator/output/kube_kong_ingress.py
deploy_config_generator/output/kube_kong_plugin.py
deploy_config_generator/output/kube_namespace.py
deploy_config_generator/output/kube_pdb.py
deploy_config_generator/output/kube_pv.py
deploy_config_generator/output/kube_pvc.py
deploy_config_generator/output/kube_secret.py
deploy_config_generator/output/kube_service.py
deploy_config_generator/output/kube_serviceaccount.py
deploy_config_generator/output/kube_servicemonitor.py
deploy_config_generator/output/kube_statefulset.py
deploy_config_generator/output/marathon.py
deploy_config_generator/output/metronome.py