Metadata-Version: 2.4
Name: deploy-config-generator
Version: 2.30.0
Summary: Utility to generate service deploy configurations
Home-page: https://github.com/ApplauseOSS/deploy-config-generator
Author: Applause
Author-email: ops@applause.com
License: MIT
Requires-Python: >=3
License-File: LICENSE
Requires-Dist: Jinja2>=2.11
Requires-Dist: PyYAML
Dynamic: author
Dynamic: author-email
Dynamic: description
Dynamic: description-content-type
Dynamic: home-page
Dynamic: license
Dynamic: license-file
Dynamic: requires-dist
Dynamic: requires-python
Dynamic: summary
